LFSpy/LFS.py
LFSpy/__init__.py
LFSpy/tests/__init__.py
LFSpy/tests/matlab_Data.mat
LFSpy/tests/test_lfs.py
LFSpy-1.0.4.dist-info/LICENSE
LFSpy-1.0.4.dist-info/METADATA
LFSpy-1.0.4.dist-info/WHEEL
LFSpy-1.0.4.dist-info/top_level.txt
LFSpy-1.0.4.dist-info/RECORD
