Metadata-Version: 2.1
Name: LFSpy
Version: 1.0.4
Summary: UNKNOWN
Home-page: https://github.com/McMasterRS/LFSpy/
Author: Oliver Cook, Kiret Dhindsa, Thomas Mudway, Areeb Khawaja, Ron Harwood and Ranil Sonnadara   
License: UNKNOWN
Platform: UNKNOWN
Classifier: Programming Language :: Python :: 3
Classifier: License :: OSI Approved :: BSD License
Classifier: Operating System :: OS Independent
Requires-Python: >=3.6
Requires-Dist: numpy (>=1.14)
Requires-Dist: scipy (>=1.1)
Requires-Dist: scikit-learn (>=0.18.2)
Provides-Extra: test
Requires-Dist: pytest (>=5.0.0) ; extra == 'test'
